<!--
  The Titanium UX Template Library
  http://www.uxmobilepatterns.com
-->
<Alloy>
	<TableView onClick="openItem" id="tableView">
		<TableViewRow title="Article Detail Complete" controller="templates/DetailSample1" hasChild="true"></TableViewRow>
		<TableViewRow title="Sign up sample" controller="templates/Signup" hasChild="true"></TableViewRow>

		<TableViewRow title="Settings" controller="templates/Settings" hasChild="true"></TableViewRow>
		<TableViewRow><Widget src="ti.ux.spacer"></Widget></TableViewRow>
		<TableViewRow title="Font Awesome charcodes" controller="templates/IconFonts" hasChild="true"></TableViewRow>
		
	</TableView>
</Alloy>

